COPYRIGHT
Changelog
MANIFEST.in
README.md
setup.py
docs/Makefile
docs/_static
docs/commands.rst
docs/conf.py
docs/examples.rst
docs/index.rst
docs/installation.rst
docs/library.rst
docs/overview.rst
docs/setup.rst
docs/upgrade.rst
docs/usage.rst
docs/.ropeproject/config.py
docs/.ropeproject/globalnames
docs/.ropeproject/history
docs/.ropeproject/objectdb
docs/examplesdir/astakos.rst
docs/examplesdir/blockstorage.rst
docs/examplesdir/configuration.rst
docs/examplesdir/imageregister.rst
docs/examplesdir/listing.rst
docs/examplesdir/network.rst
docs/examplesdir/server.rst
docs/examplesdir/sharing.rst
docs/examplesdir/updownload.rst
docs/images/kamaki-logo.png
docs/library/clients.rst
docs/library/errors.rst
docs/library/extend.rst
docs/library/get-started.rst
docs/library/logging.rst
docs/library/ssl.rst
docs/library/examples/astakos-authenticate.py
docs/library/examples/astakos-project-info.py
docs/library/examples/astakos-project-quotas.py
docs/library/examples/astakos-project-reassign.py
docs/library/examples/astakos-quotas.py
docs/library/examples/astakos-resource-allocation.py
docs/library/examples/compute-create.py
docs/library/examples/compute-image-flavor.py
docs/library/examples/compute-quotas.py
docs/library/examples/compute-reassign-resize.py
docs/library/examples/compute-reboot.py
docs/library/examples/compute-wait.py
docs/library/examples/image-list.py
docs/library/examples/image-register.py
docs/library/examples/image-unregister.py
docs/library/examples/network-cluster.py
docs/library/examples/network-ip.py
docs/library/examples/network-vpn.py
docs/library/examples/pithos-download-upload.py
docs/library/examples/pithos-init.py
docs/library/examples/pithos-list.py
docs/library/examples/pithos-move-copy-delete.py
docs/library/examples/pithos-reassign.py
docs/library/examples/volume-plug-unplug.py
docs/man/kamaki-shell.rst
docs/man/kamaki.rst
docs/upgrade/upgrade-0.13.rst
kamaki/__init__.py
kamaki/defaults.py
kamaki/version.py
kamaki.egg-info/PKG-INFO
kamaki.egg-info/SOURCES.txt
kamaki.egg-info/dependency_links.txt
kamaki.egg-info/entry_points.txt
kamaki.egg-info/requires.txt
kamaki.egg-info/top_level.txt
kamaki/cli/__init__.py
