Metadata-Version: 1.1
Name: kamaki
Version: 0.15
Summary: A multipurpose, interactive command-line tool, and also a client development library for managing OpenStack clouds.
Home-page: http://www.synnefo.org
Author: Synnefo development team
Author-email: synnefo-devel@googlegroups.com
License: BSD
Download-URL: https://pypi.python.org/pypi/kamaki
Platform: UNKNOWN
Classifier: Operating System :: OS Independent
Classifier: Programming Language :: Python :: 2.6
Classifier: Programming Language :: Python :: 2.7
Classifier: Intended Audience :: Developers
Classifier: Intended Audience :: System Administrators
Classifier: Environment :: Console
Classifier: License :: OSI Approved :: BSD License
Classifier: Natural Language :: English
Classifier: Topic :: System :: Shells
Classifier: Topic :: Software Development :: Libraries :: Python Modules
Classifier: Topic :: Utilities
